litestar_browser_reload/__about__.py
litestar_browser_reload/__init__.py
litestar_browser_reload/py.pyped
litestar_browser_reload/static/reload-listener.js
litestar_browser_reload/static/reload-worker.js
litestar_browser_reload-0.3.0.dist-info/METADATA
litestar_browser_reload-0.3.0.dist-info/WHEEL
litestar_browser_reload-0.3.0.dist-info/licenses/LICENSE.txt
litestar_browser_reload-0.3.0.dist-info/RECORD
