Metadata-Version: 2.4
Name: litestar-browser-reload
Version: 0.3.0
Summary: Automatic browser reload plugin for Litestar, designed for development use.
Project-URL: Documentation, https://github.com/Tobi-De/litestar-browser-reload#readme
Project-URL: Issues, https://github.com/Tobi-De/litestar-browser-reload/issues
Project-URL: Source, https://github.com/Tobi-De/litestar-browser-reload
Author-email: Tobi DEGNON <tobidegnon@proton.me>
License-File: LICENSE.txt
Keywords: autoreload,browser,litestar
Classifier: Development Status :: 4 - Beta
Classifier: Intended Audience :: Developers
Classifier: Programming Language :: Python
Classifier: Programming Language :: Python :: 3 :: Only
Classifier: Programming Language :: Python :: 3.8
Classifier: Programming Language :: Python :: 3.9
Classifier: Programming Language :: Python :: 3.10
Classifier: Programming Language :: Python :: 3.11
Classifier: Programming Language :: Python :: 3.12
Classifier: Programming Language :: Python :: Implementation :: CPython
Classifier: Programming Language :: Python :: Implementation :: PyPy
Classifier: Topic :: Software Development
Classifier: Typing :: Typed
Requires-Python: >=3.8
Requires-Dist: litestar[standard]
Requires-Dist: watchfiles
